{"metadata": {"dbt_schema_version": "https://schemas.getdbt.com/dbt/run-results/v4.json", "dbt_version": "1.0.1", "generated_at": "2022-01-23T20:06:26.832148Z", "invocation_id": "b21af24b-5897-4851-aed6-a145d17a8781", "env": {}}, "results": [{"status": "success", "timing": [{"name": "compile", "started_at": "2022-01-23T20:05:40.964895Z", "completed_at": "2022-01-23T20:05:40.979570Z"}, {"name": "execute", "started_at": "2022-01-23T20:05:40.979867Z", "completed_at": "2022-01-23T20:05:42.886114Z"}], "thread_id": "Thread-3", "execution_time": 2.1227662563323975, "adapter_response": {"_message": "SUCCESS 1", "code": "SUCCESS", "rows_affected": 1}, "message": "SUCCESS 1", "failures": null, "unique_id": "model.assetmanagement.temp_trader"}, {"status": "success", "timing": [{"name": "compile", "started_at": "2022-01-23T20:05:40.959363Z", "completed_at": "2022-01-23T20:05:40.986345Z"}, {"name": "execute", "started_at": "2022-01-23T20:05:40.986611Z", "completed_at": "2022-01-23T20:05:43.242171Z"}], "thread_id": "Thread-1", "execution_time": 2.4639744758605957, "adapter_response": {"_message": "SUCCESS 1", "code": "SUCCESS", "rows_affected": 1}, "message": "SUCCESS 1", "failures": null, "unique_id": "model.assetmanagement.stg_company_profile"}, {"status": "success", "timing": [{"name": "compile", "started_at": "2022-01-23T20:05:40.960952Z", "completed_at": "2022-01-23T20:05:40.981249Z"}, {"name": "execute", "started_at": "2022-01-23T20:05:40.981529Z", "completed_at": "2022-01-23T20:05:58.000107Z"}], "thread_id": "Thread-2", "execution_time": 17.22843861579895, "adapter_response": {"_message": "SUCCESS 1", "code": "SUCCESS", "rows_affected": 1}, "message": "SUCCESS 1", "failures": null, "unique_id": "model.assetmanagement.stg_stock_history"}, {"status": "success", "timing": [{"name": "compile", "started_at": "2022-01-23T20:05:58.191534Z", "completed_at": "2022-01-23T20:05:58.213971Z"}, {"name": "execute", "started_at": "2022-01-23T20:05:58.214236Z", "completed_at": "2022-01-23T20:06:00.957380Z"}], "thread_id": "Thread-4", "execution_time": 2.9526541233062744, "adapter_response": {"_message": "SUCCESS 1", "code": "SUCCESS", "rows_affected": 1}, "message": "SUCCESS 1", "failures": null, "unique_id": "model.assetmanagement.stg_stock_latest"}, {"status": "success", "timing": [{"name": "compile", "started_at": "2022-01-23T20:06:01.146176Z", "completed_at": "2022-01-23T20:06:01.166471Z"}, {"name": "execute", "started_at": "2022-01-23T20:06:01.166773Z", "completed_at": "2022-01-23T20:06:04.059327Z"}], "thread_id": "Thread-1", "execution_time": 3.1039743423461914, "adapter_response": {"_message": "SUCCESS 1", "code": "SUCCESS", "rows_affected": 1}, "message": "SUCCESS 1", "failures": null, "unique_id": "model.assetmanagement.temp_watchlist"}, {"status": "success", "timing": [{"name": "compile", "started_at": "2022-01-23T20:06:04.252151Z", "completed_at": "2022-01-23T20:06:04.269616Z"}, {"name": "execute", "started_at": "2022-01-23T20:06:04.269892Z", "completed_at": "2022-01-23T20:06:05.819767Z"}], "thread_id": "Thread-3", "execution_time": 1.8078057765960693, "adapter_response": {"_message": "SUCCESS 1", "code": "SUCCESS", "rows_affected": 1}, "message": "SUCCESS 1", "failures": null, "unique_id": "model.assetmanagement.watchlist"}, {"status": "success", "timing": [{"name": "compile", "started_at": "2022-01-23T20:06:06.061945Z", "completed_at": "2022-01-23T20:06:06.079637Z"}, {"name": "execute", "started_at": "2022-01-23T20:06:06.079898Z", "completed_at": "2022-01-23T20:06:22.135043Z"}], "thread_id": "Thread-2", "execution_time": 16.254725217819214, "adapter_response": {"_message": "SUCCESS 1", "code": "SUCCESS", "rows_affected": 1}, "message": "SUCCESS 1", "failures": null, "unique_id": "model.assetmanagement.trade"}, {"status": "success", "timing": [{"name": "compile", "started_at": "2022-01-23T20:06:22.318390Z", "completed_at": "2022-01-23T20:06:22.334705Z"}, {"name": "execute", "started_at": "2022-01-23T20:06:22.334962Z", "completed_at": "2022-01-23T20:06:23.328074Z"}], "thread_id": "Thread-4", "execution_time": 1.4628453254699707, "adapter_response": {"_message": "SUCCESS 1", "code": "SUCCESS", "rows_affected": 1}, "message": "SUCCESS 1", "failures": null, "unique_id": "model.assetmanagement.position"}, {"status": "success", "timing": [{"name": "compile", "started_at": "2022-01-23T20:06:23.783278Z", "completed_at": "2022-01-23T20:06:23.800438Z"}, {"name": "execute", "started_at": "2022-01-23T20:06:23.800710Z", "completed_at": "2022-01-23T20:06:24.621143Z"}], "thread_id": "Thread-1", "execution_time": 1.0296261310577393, "adapter_response": {"_message": "SUCCESS 1", "code": "SUCCESS", "rows_affected": 1}, "message": "SUCCESS 1", "failures": null, "unique_id": "model.assetmanagement.share_now"}, {"status": "success", "timing": [{"name": "compile", "started_at": "2022-01-23T20:06:24.814625Z", "completed_at": "2022-01-23T20:06:24.829795Z"}, {"name": "execute", "started_at": "2022-01-23T20:06:24.830051Z", "completed_at": "2022-01-23T20:06:25.639451Z"}], "thread_id": "Thread-3", "execution_time": 1.0186526775360107, "adapter_response": {"_message": "SUCCESS 1", "code": "SUCCESS", "rows_affected": 1}, "message": "SUCCESS 1", "failures": null, "unique_id": "model.assetmanagement.position_now"}], "elapsed_time": 48.470805168151855, "args": {"write_json": true, "use_colors": true, "printer_width": 80, "version_check": true, "partial_parse": true, "static_parser": true, "profiles_dir": "/usr/src/develop/.dbt", "send_anonymous_usage_stats": true, "event_buffer_size": 100000, "vars": "{}\n", "which": "run", "rpc_method": "run", "indirect_selection": "eager"}}